naja_atra_asgi/__init__.py
naja_atra_asgi/asgi_request_handler.py
naja_atra_asgi-1.0.1.dist-info/LICENSE
naja_atra_asgi-1.0.1.dist-info/METADATA
naja_atra_asgi-1.0.1.dist-info/WHEEL
naja_atra_asgi-1.0.1.dist-info/top_level.txt
naja_atra_asgi-1.0.1.dist-info/RECORD
