Metadata-Version: 2.1
Name: naja-atra-asgi
Version: 1.0.1
Summary: This is a simple http server, use MVC like design.
Author-email: keijack <keijack.wu@gmail.com>
License: MIT License
Project-URL: homepage, https://github.com/naja-atra/naja-atra-asgi
Project-URL: repository, https://github.com/naja-atra/naja-atra-asgi
Keywords: http-server,websocket,http,web,web-server
Classifier: Programming Language :: Python :: 3
Classifier: License :: OSI Approved :: MIT License
Classifier: Operating System :: OS Independent
Requires-Python: >=3.7
License-File: LICENSE
Requires-Dist: naja-atra
Provides-Extra: test
Requires-Dist: pytest ; extra == 'test'
Requires-Dist: uvicorn[standard] ; extra == 'test'
Requires-Dist: websocket-client ; extra == 'test'
